maica/__init__.py
maica/chem/__init__.py
maica/chem/base.py
maica/chem/crystal.py
maica/chem/formula.py
maica/chem/molecule.py
maica/core/__init__.py
maica/core/env.py
maica/core/sys.py
maica/data/__init__.py
maica/data/base.py
maica/data/crystal.py
maica/data/formula.py
maica/data/graph.py
maica/data/molecule.py
maica/data/util.py
maica/data/vector.py
maica/data/visualization.py
maica/ml/__init__.py
maica/ml/base.py
maica/ml/embedding.py
maica/ml/fnn.py
maica/ml/gnn.py
maica/ml/nn.py
maica/ml/util.py
maica/ml_old/__init__.py
maica/ml_old/base.py
maica/ml_old/eval.py
maica/ml_old/gnn.py
maica/ml_old/nn.py
maica/ml_old/util.py
maica/util/__init__.py
maica/util/analysis.py
maica/util/visualization.py
maica-0.1.2.dist-info/LICENSE
maica-0.1.2.dist-info/METADATA
maica-0.1.2.dist-info/WHEEL
maica-0.1.2.dist-info/top_level.txt
maica-0.1.2.dist-info/RECORD
