Metadata-Version: 2.1
Name: maica
Version: 0.1.2
Summary: Python package for chemical machine learning.
Home-page: UNKNOWN
Author: Gyoung S. Na
Author-email: ngs0@krict.re.kr
License: UNKNOWN
Keywords: chemical science,materials science,artificial intelligence,machine learning
Platform: UNKNOWN
Requires-Python: >=3.7
